{"nodes": [{"id": "gallery_3", "label": "Gallery 3 \u2014 Tasks List (light)", "file_type": "image", "source_file": "deploy/umbrel/gallery/3.jpg", "source_location": null, "source_url": null, "captured_at": null, "author": null, "contributor": null}, {"id": "concept_tasks_module", "label": "Tasks module", "file_type": "image", "source_file": "deploy/umbrel/gallery/3.jpg", "source_location": null, "source_url": null, "captured_at": null, "author": null, "contributor": null}], "edges": [{"source": "gallery_3", "target": "concept_tasks_module", "relation": "references", "confidence": "INFERRED", "confidence_score": 0.95, "source_file": "deploy/umbrel/gallery/3.jpg", "source_location": null, "weight": 1.0}], "hyperedges": []}